pynenc_redis/__init__.py
pynenc_redis/builder.py
pynenc_redis/arg_cache/__init__.py
pynenc_redis/arg_cache/redis_arg_cache.py
pynenc_redis/broker/__init__.py
pynenc_redis/broker/redis_broker.py
pynenc_redis/conf/__init__.py
pynenc_redis/conf/config_arg_cache.py
pynenc_redis/conf/config_broker.py
pynenc_redis/conf/config_orchestrator.py
pynenc_redis/conf/config_redis.py
pynenc_redis/conf/config_state_backend.py
pynenc_redis/conf/config_trigger.py
pynenc_redis/orchestrator/__init__.py
pynenc_redis/orchestrator/redis_orchestrator.py
pynenc_redis/state_backend/__init__.py
pynenc_redis/state_backend/redis_state_backend.py
pynenc_redis/trigger/__init__.py
pynenc_redis/trigger/redis_trigger.py
pynenc_redis/util/__init__.py
pynenc_redis/util/mongo_client.py
pynenc_redis/util/redis_keys.py
pynenc_redis-0.1.4.dist-info/METADATA
pynenc_redis-0.1.4.dist-info/WHEEL
pynenc_redis-0.1.4.dist-info/entry_points.txt
pynenc_redis-0.1.4.dist-info/licenses/LICENSE
pynenc_redis-0.1.4.dist-info/RECORD
